XiandaiKeyanZhibei/README.md
XiandaiKeyanZhibei/__init__.py
XiandaiKeyanZhibei/__main__.py
XiandaiKeyanZhibei/file.epub
XiandaiKeyanZhibei/index.html
XiandaiKeyanZhibei/css/__init__.py
XiandaiKeyanZhibei/css/annotations.css
XiandaiKeyanZhibei/css/main.css
XiandaiKeyanZhibei/css/normalize.css
XiandaiKeyanZhibei/css/popup.css
XiandaiKeyanZhibei/font/__init__.py
XiandaiKeyanZhibei/font/fontello.eot
XiandaiKeyanZhibei/font/fontello.svg
XiandaiKeyanZhibei/font/fontello.ttf
XiandaiKeyanZhibei/font/fontello.woff
XiandaiKeyanZhibei/img/__init__.py
XiandaiKeyanZhibei/img/annotator-glyph-sprite.png
XiandaiKeyanZhibei/img/annotator-icon-sprite.png
XiandaiKeyanZhibei/img/apple-touch-icon.png
XiandaiKeyanZhibei/img/cancelfullscreen.png
XiandaiKeyanZhibei/img/close.png
XiandaiKeyanZhibei/img/fullscreen.png
XiandaiKeyanZhibei/img/loader.gif
XiandaiKeyanZhibei/img/menu-icon.png
XiandaiKeyanZhibei/img/save.png
XiandaiKeyanZhibei/img/saved.png
XiandaiKeyanZhibei/img/settings-s.png
XiandaiKeyanZhibei/img/settings.png
XiandaiKeyanZhibei/img/star.png
XiandaiKeyanZhibei/js/__init__.py
XiandaiKeyanZhibei/js/epub.js
XiandaiKeyanZhibei/js/epub.min.js
XiandaiKeyanZhibei/js/epub.min.map
XiandaiKeyanZhibei/js/hooks.min.js
XiandaiKeyanZhibei/js/hooks.min.map
XiandaiKeyanZhibei/js/reader.js
XiandaiKeyanZhibei/js/reader.js.map
XiandaiKeyanZhibei/js/reader.min.js
XiandaiKeyanZhibei/js/reader.min.map
XiandaiKeyanZhibei/js/hooks/__init__.py
XiandaiKeyanZhibei/js/hooks/extensions/__init__.py
XiandaiKeyanZhibei/js/hooks/extensions/highlight.js
XiandaiKeyanZhibei/js/libs/__init__.py
XiandaiKeyanZhibei/js/libs/jquery.min.js
XiandaiKeyanZhibei/js/libs/localforage.min.js
XiandaiKeyanZhibei/js/libs/screenfull.js
XiandaiKeyanZhibei/js/libs/screenfull.min.js
XiandaiKeyanZhibei/js/libs/zip.min.js
XiandaiKeyanZhibei/js/plugins/__init__.py
XiandaiKeyanZhibei/js/plugins/hypothesis.js
XiandaiKeyanZhibei/js/plugins/search.js
xiandai_keyan_zhibei-2024.3.6.0.dist-info/METADATA
xiandai_keyan_zhibei-2024.3.6.0.dist-info/WHEEL
xiandai_keyan_zhibei-2024.3.6.0.dist-info/entry_points.txt
xiandai_keyan_zhibei-2024.3.6.0.dist-info/top_level.txt
xiandai_keyan_zhibei-2024.3.6.0.dist-info/RECORD
